faststream/__about__.py
faststream/__init__.py
faststream/__main__.py
faststream/_internal/__init__.py
faststream/_internal/_compat.py
faststream/_internal/application.py
faststream/_internal/basic_types.py
faststream/_internal/broker/__init__.py
faststream/_internal/broker/broker.py
faststream/_internal/broker/pub_base.py
faststream/_internal/broker/registrator.py
faststream/_internal/broker/router.py
faststream/_internal/cli/__init__.py
faststream/_internal/cli/docs.py
faststream/_internal/cli/dto.py
faststream/_internal/cli/main.py
faststream/_internal/cli/options.py
faststream/_internal/cli/supervisors/__init__.py
faststream/_internal/cli/supervisors/asgi_multiprocess.py
faststream/_internal/cli/supervisors/basereload.py
faststream/_internal/cli/supervisors/multiprocess.py
faststream/_internal/cli/supervisors/utils.py
faststream/_internal/cli/supervisors/watchfiles.py
faststream/_internal/cli/utils/__init__.py
faststream/_internal/cli/utils/errors.py
faststream/_internal/cli/utils/imports.py
faststream/_internal/cli/utils/logs.py
faststream/_internal/cli/utils/parser.py
faststream/_internal/configs/__init__.py
faststream/_internal/configs/broker.py
faststream/_internal/configs/endpoint.py
faststream/_internal/configs/specification.py
faststream/_internal/constants.py
faststream/_internal/context/__init__.py
faststream/_internal/context/context_type.py
faststream/_internal/context/repository.py
faststream/_internal/context/resolve.py
faststream/_internal/di/__init__.py
faststream/_internal/di/config.py
faststream/_internal/endpoint/__init__.py
faststream/_internal/endpoint/call_wrapper.py
faststream/_internal/endpoint/publisher/__init__.py
faststream/_internal/endpoint/publisher/fake.py
faststream/_internal/endpoint/publisher/proto.py
faststream/_internal/endpoint/publisher/specification.py
faststream/_internal/endpoint/publisher/usecase.py
faststream/_internal/endpoint/subscriber/__init__.py
faststream/_internal/endpoint/subscriber/call_item.py
faststream-0.6.4.dist-info/licenses/LICENSE
faststream-0.6.4.dist-info/WHEEL
faststream-0.6.4.dist-info/entry_points.txt
faststream-0.6.4.dist-info/METADATA
faststream-0.6.4.dist-info/RECORD
