Metadata-Version: 2.4
Name: faststream
Version: 0.6.4
Summary: FastStream: the simplest way to work with a messaging queues
Keywords: rabbitmq,kafka,framework,nats,redis,message brokers
Author: AG2AI, Nikita Pastukhov
Author-email: AG2AI <support@ag2.ai>, Nikita Pastukhov <nikita@pastukhov-dev.ru>
License-Expression: Apache-2.0
License-File: LICENSE
Classifier: Development Status :: 5 - Production/Stable
Classifier: License :: OSI Approved :: Apache Software License
Classifier: Programming Language :: Python
Classifier: Programming Language :: Python :: Implementation :: CPython
Classifier: Programming Language :: Python :: 3
Classifier: Programming Language :: Python :: 3 :: Only
Classifier: Programming Language :: Python :: 3.10
Classifier: Programming Language :: Python :: 3.11
Classifier: Programming Language :: Python :: 3.12
Classifier: Programming Language :: Python :: 3.13
Classifier: Programming Language :: Python :: 3.14
Classifier: Operating System :: OS Independent
Classifier: Topic :: Software Development :: Libraries :: Application Frameworks
Classifier: Topic :: Software Development :: Libraries :: Python Modules
Classifier: Topic :: Software Development :: Libraries
Classifier: Topic :: Software Development
Classifier: Topic :: System :: Networking
Classifier: Topic :: System :: Distributed Computing
Classifier: Typing :: Typed
Classifier: Intended Audience :: Developers
Classifier: Intended Audience :: Information Technology
Classifier: Intended Audience :: System Administrators
Classifier: Environment :: Web Environment
Classifier: Framework :: AsyncIO
Classifier: Framework :: Pydantic
Classifier: Framework :: Pydantic :: 1
Classifier: Framework :: Pydantic :: 2
Requires-Dist: fast-depends[pydantic]>=3.0.0
Requires-Dist: typing-extensions>=4.12.0
Requires-Dist: anyio>=4.0,<5
Requires-Dist: typer>=0.9,!=0.12,<=0.20.0 ; extra == 'cli'
Requires-Dist: watchfiles>=0.15.0,<1.2.0 ; extra == 'cli'
Requires-Dist: confluent-kafka>=2,!=2.8.1,<3 ; python_full_version < '3.13' and extra == 'confluent'
Requires-Dist: confluent-kafka>=2.6,!=2.8.1,<3 ; python_full_version >= '3.13' and extra == 'confluent'
Requires-Dist: aiokafka>=0.9,<0.13 ; extra == 'kafka'
Requires-Dist: nats-py>=2.12.0,<=3.0.0 ; extra == 'nats'
Requires-Dist: opentelemetry-sdk>=1.24.0,<2.0.0 ; extra == 'otel'
Requires-Dist: prometheus-client>=0.20.0,<0.30.0 ; extra == 'prometheus'
Requires-Dist: aio-pika>=9,<10 ; extra == 'rabbit'
Requires-Dist: redis>=5.0.0,<8.0.0 ; extra == 'redis'
Requires-Python: >=3.10
Project-URL: Discord, https://discord.gg/qFm6aSqq59
Project-URL: Documentation, https://faststream.ag2.ai/latest/getting-started/
Project-URL: Homepage, https://faststream.ag2.ai/latest/
Project-URL: Source, https://github.com/ag2ai/FastStream
Project-URL: Tracker, https://github.com/ag2ai/FastStream/issues
Provides-Extra: cli
Provides-Extra: confluent
Provides-Extra: kafka
Provides-Extra: nats
Provides-Extra: otel
Provides-Extra: prometheus
Provides-Extra: rabbit
Provides-Extra: redis
